LICENSE
README.md
setup.py
sapling/__init__.py
sapling/client.py
sapling/version.py
sapling_py.egg-info/PKG-INFO
sapling_py.egg-info/SOURCES.txt
sapling_py.egg-info/dependency_links.txt
sapling_py.egg-info/requires.txt
sapling_py.egg-info/top_level.txt
test/__init__.py