Metadata-Version: 2.1
Name: sapling-py
Version: 3.0.1
Summary: Sapling Python Client
Home-page: https://sapling.ai
Author: Sapling Intelligence
Author-email: info@sapling.ai
License: Apache License 2.0
Platform: UNKNOWN
Classifier: Development Status :: 3 - Alpha
Classifier: Programming Language :: Python :: 3
License-File: LICENSE
